{
  "collectionName": "components_main_article_grids",
  "info": {
    "name": "Article-Grid",
    "icon": "newspaper",
    "description": ""
  },
  "options": {},
  "attributes": {
    "ArticleTitle": {
      "type": "string",
      "required": true,
      "default": "Montreal"
    },
    "Subtitle": {
      "type": "string",
      "required": true,
      "default": "Suscipit posuere vestibulum odio malesuada vestibulum risus."
    },
    "Publisher": {
      "type": "string",
      "private": false,
      "required": true
    },
    "LatestArticle": {
      "type": "string"
    }
  }
}
